involution_pytorch/__init__.py
involution_pytorch/involution_pytorch.py
involution_pytorch-0.0.2.2.dist-info/LICENSE
involution_pytorch-0.0.2.2.dist-info/METADATA
involution_pytorch-0.0.2.2.dist-info/WHEEL
involution_pytorch-0.0.2.2.dist-info/top_level.txt
involution_pytorch-0.0.2.2.dist-info/RECORD
